{"nodes": [{"id": "users_calza_nigredo_website_nigredo_src_pages_index_astro", "label": "index.astro", "file_type": "code", "source_file": "src/pages/index.astro", "source_location": "L1"}, {"id": "users_calza_nigredo_website_nigredo_src_pages_index_schema", "label": "schema", "file_type": "code", "source_file": "src/pages/index.astro", "source_location": "L4"}, {"id": "users_calza_nigredo_website_nigredo_src_layouts_layout_astro", "label": "../layouts/Layout.astro", "file_type": "code", "source_file": "src/layouts/Layout.astro", "confidence": "EXTRACTED"}], "edges": [{"source": "users_calza_nigredo_website_nigredo_src_pages_index_astro", "target": "users_calza_nigredo_website_nigredo_src_pages_index_schema", "relation": "contains", "confidence": "EXTRACTED", "source_file": "src/pages/index.astro", "source_location": "L4", "weight": 1.0}, {"source": "users_calza_nigredo_website_nigredo_src_pages_index_astro", "target": "users_calza_nigredo_website_nigredo_src_layouts_layout_astro", "relation": "imports_from", "confidence": "EXTRACTED", "source_file": "src/pages/index.astro"}], "raw_calls": [{"caller_nid": "users_calza_nigredo_website_nigredo_src_pages_index_astro", "callee": "vw", "is_member_call": false, "indirect": true, "context": "argument", "source_file": "src/pages/index.astro", "source_location": "L169"}, {"caller_nid": "users_calza_nigredo_website_nigredo_src_pages_index_astro", "callee": "deg", "is_member_call": false, "indirect": true, "context": "argument", "source_file": "src/pages/index.astro", "source_location": "L174"}, {"caller_nid": "users_calza_nigredo_website_nigredo_src_pages_index_astro", "callee": "a0a0c", "is_member_call": false, "indirect": true, "context": "argument", "source_file": "src/pages/index.astro", "source_location": "L210"}, {"caller_nid": "users_calza_nigredo_website_nigredo_src_pages_index_astro", "callee": "a0a0c", "is_member_call": false, "indirect": true, "context": "argument", "source_file": "src/pages/index.astro", "source_location": "L210"}, {"caller_nid": "users_calza_nigredo_website_nigredo_src_pages_index_astro", "callee": "vw", "is_member_call": false, "indirect": true, "context": "argument", "source_file": "src/pages/index.astro", "source_location": "L216"}, {"caller_nid": "users_calza_nigredo_website_nigredo_src_pages_index_astro", "callee": "vw", "is_member_call": false, "indirect": true, "context": "argument", "source_file": "src/pages/index.astro", "source_location": "L217"}, {"caller_nid": "users_calza_nigredo_website_nigredo_src_pages_index_astro", "callee": "transparent", "is_member_call": false, "indirect": true, "context": "argument", "source_file": "src/pages/index.astro", "source_location": "L229"}, {"caller_nid": "users_calza_nigredo_website_nigredo_src_pages_index_astro", "callee": "transparent", "is_member_call": false, "indirect": true, "context": "argument", "source_file": "src/pages/index.astro", "source_location": "L230"}, {"caller_nid": "users_calza_nigredo_website_nigredo_src_pages_index_astro", "callee": "transparent", "is_member_call": false, "indirect": true, "context": "argument", "source_file": "src/pages/index.astro", "source_location": "L239"}, {"caller_nid": "users_calza_nigredo_website_nigredo_src_pages_index_astro", "callee": "transparent", "is_member_call": false, "indirect": true, "context": "argument", "source_file": "src/pages/index.astro", "source_location": "L244"}, {"caller_nid": "users_calza_nigredo_website_nigredo_src_pages_index_astro", "callee": "transparent", "is_member_call": false, "indirect": true, "context": "argument", "source_file": "src/pages/index.astro", "source_location": "L245"}, {"caller_nid": "users_calza_nigredo_website_nigredo_src_pages_index_astro", "callee": "transparent", "is_member_call": false, "indirect": true, "context": "argument", "source_file": "src/pages/index.astro", "source_location": "L246"}]}